vector_lib/__init__.py
vector_lib/functions.py
vector_lib-0.1.0.dist-info/LICENSE
vector_lib-0.1.0.dist-info/METADATA
vector_lib-0.1.0.dist-info/WHEEL
vector_lib-0.1.0.dist-info/top_level.txt
vector_lib-0.1.0.dist-info/RECORD
