Metadata-Version: 2.1
Name: vector-lib
Version: 0.1.0
Summary: Python library PoC
Home-page: UNKNOWN
Author: rsouza01@gmail.com
License: MIT
Platform: UNKNOWN
Classifier: Programming Language :: Python :: 3
Classifier: License :: OSI Approved :: MIT License
Classifier: Operating System :: OS Independent
Requires-Python: >=3.6
License-File: LICENSE
